{
    "profiles": [
        {
            "complex_modifications": {
                "parameters": {
                    "basic.to_delayed_action_delay_milliseconds": 100,
                    "basic.to_if_alone_timeout_milliseconds": 200,
                    "basic.to_if_held_down_threshold_milliseconds": 100
                },
                "rules": [
                    {
                        "description": "Press and hold j for shift.",
                        "manipulators": [
                            {
                                "conditions": [
                                    {
                                        "identifiers": [{ "is_built_in_keyboard": true }],
                                        "type": "device_if"
                                    }
                                ],
                                "from": { "key_code": "j" },
                                "to_delayed_action": {
                                    "to_if_canceled": [
                                        {
                                            "halt": true,
                                            "key_code": "j"
                                        }
                                    ],
                                    "to_if_invoked": [{ "key_code": "vk_none" }]
                                },
                                "to_if_alone": [
                                    {
                                        "halt": true,
                                        "key_code": "j"
                                    }
                                ],
                                "to_if_held_down": [
                                    {
                                        "halt": true,
                                        "key_code": "right_shift"
                                    }
                                ],
                                "type": "basic"
                            }
                        ]
                    },
                    {
                        "description": "Press and hold k for command.",
                        "manipulators": [
                            {
                                "conditions": [
                                    {
                                        "identifiers": [{ "is_built_in_keyboard": true }],
                                        "type": "device_if"
                                    }
                                ],
                                "from": { "key_code": "k" },
                                "to_delayed_action": {
                                    "to_if_canceled": [
                                        {
                                            "halt": true,
                                            "key_code": "k"
                                        }
                                    ],
                                    "to_if_invoked": [{ "key_code": "vk_none" }]
                                },
                                "to_if_alone": [
                                    {
                                        "halt": true,
                                        "key_code": "k"
                                    }
                                ],
                                "to_if_held_down": [
                                    {
                                        "halt": true,
                                        "key_code": "right_command"
                                    }
                                ],
                                "type": "basic"
                            }
                        ]
                    },
                    {
                        "description": "Press and hold f for shift.",
                        "manipulators": [
                            {
                                "conditions": [
                                    {
                                        "identifiers": [{ "is_built_in_keyboard": true }],
                                        "type": "device_if"
                                    }
                                ],
                                "from": { "key_code": "f" },
                                "to_delayed_action": {
                                    "to_if_canceled": [
                                        {
                                            "halt": true,
                                            "key_code": "f"
                                        }
                                    ],
                                    "to_if_invoked": [{ "key_code": "vk_none" }]
                                },
                                "to_if_alone": [
                                    {
                                        "halt": true,
                                        "key_code": "f"
                                    }
                                ],
                                "to_if_held_down": [
                                    {
                                        "halt": true,
                                        "key_code": "left_shift"
                                    }
                                ],
                                "type": "basic"
                            }
                        ]
                    },
                    {
                        "description": "Press and hold d for command.",
                        "manipulators": [
                            {
                                "conditions": [
                                    {
                                        "identifiers": [{ "is_built_in_keyboard": true }],
                                        "type": "device_if"
                                    }
                                ],
                                "from": { "key_code": "d" },
                                "to_delayed_action": {
                                    "to_if_canceled": [
                                        {
                                            "halt": true,
                                            "key_code": "d"
                                        }
                                    ],
                                    "to_if_invoked": [{ "key_code": "vk_none" }]
                                },
                                "to_if_alone": [
                                    {
                                        "halt": true,
                                        "key_code": "d"
                                    }
                                ],
                                "to_if_held_down": [
                                    {
                                        "halt": true,
                                        "key_code": "left_command"
                                    }
                                ],
                                "type": "basic"
                            }
                        ]
                    }
                ]
            },
            "devices": [
                {
                    "identifiers": { "is_keyboard": true },
                    "simple_modifications": [
                        {
                            "from": { "key_code": "caps_lock" },
                            "to": [{ "key_code": "left_control" }]
                        }
                    ]
                },
                {
                    "identifiers": {
                        "is_keyboard": true,
                        "product_id": 591,
                        "vendor_id": 1452
                    },
                    "simple_modifications": [
                        {
                            "from": { "key_code": "caps_lock" },
                            "to": [{ "key_code": "left_control" }]
                        }
                    ]
                }
            ],
            "name": "Default profile",
            "selected": true,
            "virtual_hid_keyboard": { "keyboard_type_v2": "ansi" }
        }
    ]
}